things_aihub/__init__.py
things_aihub/admin_rest.py
things_aihub/attribute.py
things_aihub/rest.py
things_aihub/rpc_coap.py
things_aihub/rpc_gateway_mqtt.py
things_aihub/rpc_mqtt.py
things_aihub/session.py
things_aihub/telemetry.py
aihub_things-0.5.0.dist-info/METADATA
aihub_things-0.5.0.dist-info/WHEEL
aihub_things-0.5.0.dist-info/top_level.txt
aihub_things-0.5.0.dist-info/RECORD
