Metadata-Version: 2.1
Name: aihub-things
Version: 0.5.0
Summary: aihub things sdk
Home-page: http://github.com
Author: zouqqz
Author-email: zouqqz@gmail.com
License: UNKNOWN
Keywords: sdk,aihub
Platform: UNKNOWN
Requires-Dist: paho-mqtt
Requires-Dist: requests
Requires-Dist: CoAPthon
